{
  "routeData": {
    "1-2023-09-15": [
      {
        "lat": 21.1702,
        "lng": 72.8311,
        "timestamp": "2023-09-15T08:00:00Z",
        "speed": 0
      },
      {
        "lat": 21.1722,
        "lng": 72.8321,
        "timestamp": "2023-09-15T08:15:00Z",
        "speed": 15
      },
      {
        "lat": 21.1742,
        "lng": 72.8351,
        "timestamp": "2023-09-15T08:30:00Z",
        "speed": 20
      },
      {
        "lat": 21.1762,
        "lng": 72.8401,
        "timestamp": "2023-09-15T08:45:00Z",
        "speed": 18
      }
    ],
    "2-2023-09-15": [
      {
        "lat": 21.2,
        "lng": 72.84,
        "timestamp": "2023-09-15T09:00:00Z",
        "speed": 0
      },
      {
        "lat": 21.205,
        "lng": 72.845,
        "timestamp": "2023-09-15T09:15:00Z",
        "speed": 22
      },
      {
        "lat": 21.21,
        "lng": 72.85,
        "timestamp": "2023-09-15T09:30:00Z",
        "speed": 25
      }
    ],
    "3-2023-09-15": [
      {
        "lat": 21.19,
        "lng": 72.79,
        "timestamp": "2023-09-15T10:00:00Z",
        "speed": 0
      },
      {
        "lat": 21.1925,
        "lng": 72.7925,
        "timestamp": "2023-09-15T10:15:00Z",
        "speed": 18
      },
      {
        "lat": 21.195,
        "lng": 72.795,
        "timestamp": "2023-09-15T10:30:00Z",
        "speed": 20
      }
    ],
    "4-2023-09-16": [
      {
        "lat": 21.195,
        "lng": 72.845,
        "timestamp": "2023-09-16T08:00:00Z",
        "speed": 0
      },
      {
        "lat": 21.1975,
        "lng": 72.8475,
        "timestamp": "2023-09-16T08:15:00Z",
        "speed": 15
      },
      {
        "lat": 21.2,
        "lng": 72.85,
        "timestamp": "2023-09-16T08:30:00Z",
        "speed": 18
      }
    ],
    "5-2023-09-16": [
      {
        "lat": 21.1822,
        "lng": 72.83,
        "timestamp": "2023-09-16T09:00:00Z",
        "speed": 0
      },
      {
        "lat": 21.1835,
        "lng": 72.8325,
        "timestamp": "2023-09-16T09:15:00Z",
        "speed": 12
      },
      {
        "lat": 21.185,
        "lng": 72.835,
        "timestamp": "2023-09-16T09:30:00Z",
        "speed": 15
      }
    ]
  }
}
